./.gitignore
./Dockerfile
./LICENSE
./PKG-INFO
./README.md
./kospi_kosdaq_stock_server.py
./pyproject.toml
./requirements.txt
./smithery.yaml
./uv.lock
kospi_kosdaq_stock_server_fastmcp-0.2.3.dist-info/METADATA
kospi_kosdaq_stock_server_fastmcp-0.2.3.dist-info/WHEEL
kospi_kosdaq_stock_server_fastmcp-0.2.3.dist-info/entry_points.txt
kospi_kosdaq_stock_server_fastmcp-0.2.3.dist-info/licenses/LICENSE
kospi_kosdaq_stock_server_fastmcp-0.2.3.dist-info/RECORD
