Metadata-Version: 2.4
Name: kospi-kosdaq-stock-server-fastmcp
Version: 0.2.3
Summary: KOSPI/KOSDAQ Stock Data MCP Server
Project-URL: Homepage, https://github.com/fastmcp-me/kospi-kosdaq-stock-server#readme
Project-URL: Repository, https://github.com/fastmcp-me/kospi-kosdaq-stock-server.git
Project-URL: Issues, https://github.com/fastmcp-me/kospi-kosdaq-stock-server/issues
Author-email: Sangrok Mun <munsangrok@gmail.com>
License: MIT
License-File: LICENSE
Classifier: Development Status :: 5 - Production/Stable
Classifier: License :: OSI Approved :: MIT License
Classifier: Programming Language :: Python :: 3
Classifier: Programming Language :: Python :: 3.10
Requires-Python: >=3.10
Requires-Dist: mcp>=0.1.0
Requires-Dist: pykrx
Requires-Dist: requests
Requires-Dist: setuptools
